dftlib/__init__.py
dftlib/analysis/__init__.py
dftlib/analysis/smt.py
dftlib/exceptions/__init__.py
dftlib/exceptions/exceptions.py
dftlib/io/__init__.py
dftlib/io/export_galileo.py
dftlib/io/export_json.py
dftlib/io/export_txt.py
dftlib/io/formats.py
dftlib/io/latex.py
dftlib/io/parser.py
dftlib/storage/__init__.py
dftlib/storage/dft.py
dftlib/storage/dft_be.py
dftlib/storage/dft_element.py
dftlib/storage/dft_gates.py
dftlib/tools/__init__.py
dftlib/tools/storm.py
dftlib/tools/stormpy.py
dftlib/tools/z3.py
dftlib/transformer/__init__.py
dftlib/transformer/anonymizer.py
dftlib/transformer/rewrite_rules.py
dftlib/transformer/simplifier.py
dftlib/transformer/trimming.py
dftlib/utility/__init__.py
dftlib/utility/numbers.py
dftlib/utility/os_functions.py
dftlib-0.9.0.dist-info/METADATA
dftlib-0.9.0.dist-info/WHEEL
dftlib-0.9.0.dist-info/licenses/LICENSE
dftlib-0.9.0.dist-info/RECORD
